sistr_cmd-1.1.3-py3.6.egg
build/lib/sistr/__init__.py
build/lib/sistr/sistr_cmd.py
build/lib/sistr/version.py
build/lib/sistr/misc/__init__.py
build/lib/sistr/misc/add_ref_genomes.py
build/lib/sistr/misc/csv_to_hdf.py
build/lib/sistr/misc/hc_clusters_from_cgmlst_profiles.py
build/lib/sistr/misc/reduce_to_centroid_alleles.py
build/lib/sistr/src/__init__.py
build/lib/sistr/src/logger.py
build/lib/sistr/src/mash.py
build/lib/sistr/src/parsers.py
build/lib/sistr/src/writers.py
build/lib/sistr/src/blast_wrapper/__init__.py
build/lib/sistr/src/blast_wrapper/helpers.py
build/lib/sistr/src/cgmlst/__init__.py
build/lib/sistr/src/cgmlst/msa.py
build/lib/sistr/src/cgmlst/extras/__init__.py
build/lib/sistr/src/cgmlst/extras/centroid_cgmlst_alleles.py
build/lib/sistr/src/cgmlst/extras/hclust_cutree.py
build/lib/sistr/src/qc/__init__.py
build/lib/sistr/src/qc/constants.py
build/lib/sistr/src/serovar_prediction/__init__.py
build/lib/sistr/src/serovar_prediction/constants.py
sistr/__init__.py
sistr/dbstatus.txt
sistr/sistr_cmd.py
sistr/version.py
sistr/data/._Salmonella-serotype_serogroup_antigen_table-WHO_2007.csv
sistr/data/._antigens
sistr/data/._cgmlst
sistr/data/._genomes-to-serovar.txt
sistr/data/._genomes-to-subspecies.txt
sistr/data/._sistr.msh
sistr/data/Salmonella-serotype_serogroup_antigen_table-WHO_2007.csv
sistr/data/genomes-to-serovar.txt
sistr/data/genomes-to-subspecies.txt
sistr/data/serovar-list.txt
sistr/data/sistr.msh
sistr/data/antigens/._fliC.fasta
sistr/data/antigens/._fljB.fasta
sistr/data/antigens/._wzx.fasta
sistr/data/antigens/._wzy.fasta
sistr/data/antigens/fliC.fasta
sistr/data/antigens/fljB.fasta
sistr/data/antigens/wzx.fasta
sistr/data/antigens/wzy.fasta
sistr/data/cgmlst/._README.md
sistr/data/cgmlst/._cgmlst-centroid.fasta
sistr/data/cgmlst/._cgmlst-full.fasta
sistr/data/cgmlst/._cgmlst-profiles.hdf
sistr/data/cgmlst/README.md
sistr/data/cgmlst/cgmlst-centroid.fasta
sistr/data/cgmlst/cgmlst-full.fasta
sistr/data/cgmlst/cgmlst-profiles.hdf
sistr_cmd-1.1.3.dist-info/LICENSE
sistr_cmd-1.1.3.dist-info/METADATA
sistr_cmd-1.1.3.dist-info/WHEEL
sistr_cmd-1.1.3.dist-info/entry_points.txt
sistr_cmd-1.1.3.dist-info/top_level.txt
sistr_cmd-1.1.3.dist-info/RECORD
