Metadata-Version: 2.1
Name: sistr-cmd
Version: 1.1.3
Summary: Serovar predictions from Salmonella whole-genome sequence assemblies by determination of antigen geneand cgMLST gene alleles using BLAST. Mash MinHash can also be used for serovar prediction.
Home-page: https://github.com/phac-nml/sistr_cmd
Author: Peter Kruczkiewicz
Author-email: peter.kruczkiewicz@gmail.com
License: Apache 2.0
Keywords: Salmonella serotyping genotyping cgMLST BLAST Mash MinHash
Platform: UNKNOWN
Classifier: Environment :: Console
Classifier: License :: OSI Approved :: Apache Software License
Classifier: Intended Audience :: Science/Research
Classifier: Topic :: Scientific/Engineering
Classifier: Topic :: Scientific/Engineering :: Bio-Informatics
Classifier: Programming Language :: Python
Classifier: Programming Language :: Python :: 3.4
Classifier: Programming Language :: Python :: 3.5
Classifier: Programming Language :: Python :: 3.6
Classifier: Programming Language :: Python :: Implementation :: CPython
Classifier: Operating System :: POSIX :: Linux
License-File: LICENSE
Requires-Dist: numpy (<2,>=1.11.1)
Requires-Dist: tables (<4,>=3.3.0)
Requires-Dist: pandas (<3,>=0.22.0)
Requires-Dist: pycurl (<8,>=7.43.0)
Requires-Dist: scipy (<2,>=1.1.0)
Provides-Extra: test
Requires-Dist: pytest (>=2.9.2) ; extra == 'test'
